xensispy/__init__.py
xensispy/auth.py
xensispy/avatar.py
xensispy/client.py
xensispy/enums.py
xensispy/errors.py
xensispy/friend.py
xensispy/http.py
xensispy/message.py
xensispy/news.py
xensispy/party.py
xensispy/playlist.py
xensispy/presence.py
xensispy/stats.py
xensispy/store.py
xensispy/typedefs.py
xensispy/user.py
xensispy/utils.py
xensispy/xmpp.py
xensispy/ext/commands/__init__.py
xensispy/ext/commands/_types.py
xensispy/ext/commands/bot.py
xensispy/ext/commands/cog.py
xensispy/ext/commands/context.py
xensispy/ext/commands/converter.py
xensispy/ext/commands/cooldown.py
xensispy/ext/commands/core.py
xensispy/ext/commands/errors.py
xensispy/ext/commands/help.py
xensispy/ext/commands/typedefs.py
xensispy/ext/commands/view.py
xensispy-4.0.0a1.dist-info/METADATA
xensispy-4.0.0a1.dist-info/WHEEL
xensispy-4.0.0a1.dist-info/top_level.txt
xensispy-4.0.0a1.dist-info/RECORD
