Metadata-Version: 2.1
Name: xensispy
Version: 4.0.0a1
Summary: Library for interacting with fortnite services
Home-page: https://github.com/Aspect2222/fortnitepy
Author: Terbau
License: MIT
Project-URL: Documentation, https://fortnitepy.readthedocs.io/en/latest/
Project-URL: Issue tracker, https://github.com/Terbau/fortnitepy/issues
Classifier: License :: OSI Approved :: MIT License
Classifier: Intended Audience :: Developers
Classifier: Natural Language :: English
Classifier: Operating System :: OS Independent
Classifier: Programming Language :: Python :: 3.5
Classifier: Programming Language :: Python :: 3.6
Classifier: Programming Language :: Python :: 3.7
Classifier: Programming Language :: Python :: 3.8
Classifier: Programming Language :: Python :: 3.9
Classifier: Programming Language :: Python :: 3.10
Classifier: Topic :: Internet
Classifier: Topic :: Software Development :: Libraries
Classifier: Topic :: Software Development :: Libraries :: Python Modules
Classifier: Topic :: Utilities
Requires-Python: >=3.5.3
Requires-Dist: aiohttp (>=3.3)
Requires-Dist: aioxmpp (>=0.10.4)
Provides-Extra: docs
Requires-Dist: sphinxcontrib-trio (==1.1.2) ; extra == 'docs'
Requires-Dist: furo (==2021.4.11b34) ; extra == 'docs'
Requires-Dist: Jinja2 (<3.1) ; extra == 'docs'
